mkhaled/__init__.py
mkhaled/built_in_examples.py
mkhaled/code_manager.py
mkhaled-0.0.7.dist-info/LICENSE
mkhaled-0.0.7.dist-info/METADATA
mkhaled-0.0.7.dist-info/WHEEL
mkhaled-0.0.7.dist-info/top_level.txt
mkhaled-0.0.7.dist-info/RECORD
